MagicTK/__init__.py
MagicTK/animations.py
MagicTK/base.py
MagicTK/graphics.py
MagicTK/tools.py
MagicTK/widgets.py
MagicTKTool-1.0.0b1.dist-info/LICENSE
MagicTKTool-1.0.0b1.dist-info/METADATA
MagicTKTool-1.0.0b1.dist-info/WHEEL
MagicTKTool-1.0.0b1.dist-info/top_level.txt
MagicTKTool-1.0.0b1.dist-info/RECORD
