Metadata-Version: 2.1
Name: MagicTKTool
Version: 1.0.0b1
Summary: A UI package by tkinter
Home-page: https://github.com/codecrafter-tl/magictk
Author: CodeCrafter-TL
Author-email: 1825456084@qq.com
Classifier: Programming Language :: Python :: 3
Classifier: License :: OSI Approved :: MIT License
Classifier: Operating System :: OS Independent
License-File: LICENSE
